setup.py
cqparts_fasteners/LICENSE
cqparts_fasteners/__init__.py
cqparts_fasteners/bolts.py
cqparts_fasteners/female.py
cqparts_fasteners/male.py
cqparts_fasteners/nuts.py
cqparts_fasteners/params.py
cqparts_fasteners/screws.py
cqparts_fasteners/washers.py
cqparts_fasteners.egg-info/PKG-INFO
cqparts_fasteners.egg-info/SOURCES.txt
cqparts_fasteners.egg-info/dependency_links.txt
cqparts_fasteners.egg-info/not-zip-safe
cqparts_fasteners.egg-info/requires.txt
cqparts_fasteners.egg-info/top_level.txt
cqparts_fasteners/catalogue/boltdepot-bolts.json
cqparts_fasteners/catalogue/boltdepot-nuts.json
cqparts_fasteners/catalogue/boltdepot-woodscrews.json
cqparts_fasteners/fasteners/__init__.py
cqparts_fasteners/fasteners/base.py
cqparts_fasteners/fasteners/nutbolt.py
cqparts_fasteners/fasteners/screw.py
cqparts_fasteners/solidtypes/__init__.py
cqparts_fasteners/solidtypes/fastener_heads/__init__.py
cqparts_fasteners/solidtypes/fastener_heads/base.py
cqparts_fasteners/solidtypes/fastener_heads/counter_sunk.py
cqparts_fasteners/solidtypes/fastener_heads/cylindrical.py
cqparts_fasteners/solidtypes/fastener_heads/driven.py
cqparts_fasteners/solidtypes/screw_drives/__init__.py
cqparts_fasteners/solidtypes/screw_drives/base.py
cqparts_fasteners/solidtypes/screw_drives/cruciform.py
cqparts_fasteners/solidtypes/screw_drives/hex.py
cqparts_fasteners/solidtypes/screw_drives/slotted.py
cqparts_fasteners/solidtypes/screw_drives/square.py
cqparts_fasteners/solidtypes/screw_drives/tamper_resistant.py
cqparts_fasteners/solidtypes/threads/__init__.py
cqparts_fasteners/solidtypes/threads/ball_screw.py
cqparts_fasteners/solidtypes/threads/base.py
cqparts_fasteners/solidtypes/threads/iso68.py
cqparts_fasteners/solidtypes/threads/triangular.py
cqparts_fasteners/utils/__init__.py
cqparts_fasteners/utils/_casting.py
cqparts_fasteners/utils/applicator.py
cqparts_fasteners/utils/evaluator.py
cqparts_fasteners/utils/selector.py